whisper_cpp_python/__init__.py
whisper_cpp_python/whisper.py
whisper_cpp_python-0.1.6.dist-info/METADATA
whisper_cpp_python-0.1.6.dist-info/WHEEL
whisper_cpp_python-0.1.6.dist-info/RECORD
